mudstring/__init__.py
mudstring/demo.py
mudstring/util.py
mudstring-0.5.0.dist-info/LICENSE.txt
mudstring-0.5.0.dist-info/METADATA
mudstring-0.5.0.dist-info/WHEEL
mudstring-0.5.0.dist-info/top_level.txt
mudstring-0.5.0.dist-info/RECORD
