Metadata-Version: 2.1
Name: mudstring
Version: 0.5.0
Summary: Simple monkey-patching library to make for amazing ANSI experiences in MUDs
Home-page: https://github.com/volundmush/mudstring-python
Author: Volund
Maintainer: Volund
License: MIT
Project-URL: Source, https://github.com/volundmush/mudstring-python
Project-URL: Issue tracker, https://github.com/volundmush/mudstring-python/issues
Project-URL: Patreon, https://www.patreon.com/volund
Platform: UNKNOWN
Classifier: Programming Language :: Python :: 3 :: Only
Classifier: Programming Language :: Python :: 3.5
Classifier: Intended Audience :: Developers
Classifier: Topic :: Games/Entertainment :: Multi-User Dungeons (MUD)
Classifier: Topic :: Games/Entertainment :: Puzzle Games
Classifier: Topic :: Games/Entertainment :: Role-Playing
Classifier: Topic :: Games/Entertainment :: Simulation
Classifier: Topic :: Software Development :: Libraries :: Application Frameworks
Requires-Python: >=3.5
License-File: LICENSE.txt
